LICENSE
README.md
setup.py
rateninja/__init__.py
rateninja/rateninja.py
rateninja.egg-info/PKG-INFO
rateninja.egg-info/SOURCES.txt
rateninja.egg-info/dependency_links.txt
rateninja.egg-info/requires.txt
rateninja.egg-info/top_level.txt