Metadata-Version: 2.1
Name: rateninja
Version: 1.0.3
Summary: An asynchronous rate limiter for Python, that automatically handles rate limits and retries. Useful for APIs having strict rate limits.
Home-page: https://github.com/caesar-one/rateninja
Author: Cesare Campagnano
Author-email: cesare.campagnano@gmail.com
License: Apache License 2.0
License-File: LICENSE
Requires-Dist: tqdm
